omero/plugins/web.py
omeroweb_cred/__init__.py
omeroweb_cred/connector.py
omeroweb_cred/custom_context_processor.py
omeroweb_cred/custom_forms.py
omeroweb_cred/decorators.py
omeroweb_cred/filesessionstore.py
omeroweb_cred/httprsp.py
omeroweb_cred/manage.py
omeroweb_cred/settings.py
omeroweb_cred/urls.py
omeroweb_cred/utils.py
omeroweb_cred/version.py
omeroweb_cred/wsgi.py
omeroweb_cred/api/__init__.py
omeroweb_cred/api/api_exceptions.py
omeroweb_cred/api/api_marshal.py
omeroweb_cred/api/api_query.py
omeroweb_cred/api/api_settings.py
omeroweb_cred/api/decorators.py
omeroweb_cred/api/urls.py
omeroweb_cred/api/views.py
omeroweb_cred/feedback/__init__.py
omeroweb_cred/feedback/forms.py
omeroweb_cred/feedback/sendfeedback.py
omeroweb_cred/feedback/urls.py
omeroweb_cred/feedback/views.py
omeroweb_cred/feedback/templatetags/__init__.py
omeroweb_cred/feedback/templatetags/feedback_tags.py
omeroweb_cred/omeroauth/__init__.py
omeroweb_cred/omeroauth/oauth_settings.py
omeroweb_cred/omeroauth/openid.py
omeroweb_cred/omeroauth/providers.py
omeroweb_cred/omeroauth/urls.py
omeroweb_cred/omeroauth/views.py
omeroweb_cred/testlib/__init__.py
omeroweb_cred/webadmin/__init__.py
omeroweb_cred/webadmin/custom_forms.py
omeroweb_cred/webadmin/forms.py
omeroweb_cred/webadmin/models.py
omeroweb_cred/webadmin/urls.py
omeroweb_cred/webadmin/views.py
omeroweb_cred/webadmin/webadmin_utils.py
omeroweb_cred/webadmin/templatetags/__init__.py
omeroweb_cred/webadmin/templatetags/webadmin_tags.py
omeroweb_cred/webclient/__init__.py
omeroweb_cred/webclient/custom_forms.py
omeroweb_cred/webclient/decorators.py
omeroweb_cred/webclient/forms.py
omeroweb_cred/webclient/show.py
omeroweb_cred/webclient/tree.py
omeroweb_cred/webclient/urls.py
omeroweb_cred/webclient/views.py
omeroweb_cred/webclient/webclient_gateway.py
omeroweb_cred/webclient/webclient_utils.py
omeroweb_cred/webclient/controller/__init__.py
omeroweb_cred/webclient/controller/container.py
omeroweb_cred/webclient/controller/help.py
omero_cred-0.0.7.dist-info/LICENSE
omero_cred-0.0.7.dist-info/METADATA
omero_cred-0.0.7.dist-info/WHEEL
omero_cred-0.0.7.dist-info/top_level.txt
omero_cred-0.0.7.dist-info/RECORD
